rtd_common-0.1.3.dist-info/METADATA
rtd_common-0.1.3.dist-info/WHEEL
rtd_common/__init__.py
rtd_common/__init__.pyi
rtd_common/py.typed
rtd_common/rtd_common.cpython-312-x86_64-linux-gnu.so
rtd_common-0.1.3.dist-info/RECORD
