Metadata-Version: 2.4
Name: rtd-common
Version: 0.1.3
Summary: RFA Hil Testbench
Author: Julius Walczynski, Chee Hang Yong
